datus_starrocks/__init__.py
datus_starrocks/config.py
datus_starrocks/connector.py
datus_starrocks-0.1.2.dist-info/METADATA
datus_starrocks-0.1.2.dist-info/WHEEL
datus_starrocks-0.1.2.dist-info/entry_points.txt
datus_starrocks-0.1.2.dist-info/RECORD
