Metadata-Version: 2.4
Name: datus-starrocks
Version: 0.1.2
Summary: StarRocks database adapter for Datus
Project-URL: Homepage, https://github.com/Datus-ai/datus-db-adapters
Project-URL: Repository, https://github.com/Datus-ai/datus-db-adapters
Project-URL: Issues, https://github.com/Datus-ai/datus-db-adapters/issues
Author-email: DatusAI <support@datus.ai>
License: Apache-2.0
Keywords: adapter,database,datus,starrocks
Classifier: Development Status :: 4 - Beta
Classifier: Intended Audience :: Developers
Classifier: License :: OSI Approved :: Apache Software License
Classifier: Programming Language :: Python :: 3
Classifier: Programming Language :: Python :: 3.12
Requires-Python: >=3.12
Requires-Dist: datus-agent>0.2.1
Requires-Dist: datus-mysql>=0.1.3
Requires-Dist: pydantic>=2.0.0
Provides-Extra: test
Requires-Dist: pytest-cov>=4.0.0; extra == 'test'
Requires-Dist: pytest>=7.0.0; extra == 'test'
